py_nl2sql/__init__.py
py_nl2sql/constants/__init__.py
py_nl2sql/constants/prompts.py
py_nl2sql/constants/type.py
py_nl2sql/db_instance.py
py_nl2sql/models/llm.py
py_nl2sql/relational_database/__init__.py
py_nl2sql/relational_database/mysql_connector.py
py_nl2sql/relational_database/postgresql_connector.py
py_nl2sql/relational_database/sql_database.py
py_nl2sql/relational_database/sql_factory.py
py_nl2sql/retrieval/__init__.py
py_nl2sql/retrieval/pre_retrieval.py
py_nl2sql/retrieval/retrieval.py
py_nl2sql/utilities/__init__.py
py_nl2sql/utilities/db_state_machine.py
py_nl2sql/utilities/decorators.py
py_nl2sql/utilities/tools.py
py_nl2sql/vector_database/__init__.py
py_nl2sql/vector_database/base_vectordb.py
py_nl2sql/vector_database/faiss_wrapper.py
py_nl2sql/vector_database/pgvector_wrapper.py
py_nl2sql/workflow.py
py_nl2sql-0.0.2.dist-info/LICENSE
py_nl2sql-0.0.2.dist-info/METADATA
py_nl2sql-0.0.2.dist-info/WHEEL
py_nl2sql-0.0.2.dist-info/RECORD
